{
    "resources": [ 
        [   {   "id": "install",
                "path": "C:\\Projects\\Sitecore.Demo.Retail\\Install",
                "files": [
                    [   {   "id": "commerceInstaller", "fileName": "CommerceServer-11.4.148.exe"}   ]
                ]   
            }   
        ],
        [   {   "id": "projectDatabaseScripts",
                "path": "C:\\Projects\\Sitecore.Demo.Retail\\src\\Project\\Retail\\Database",
                "files": [
                    [   {   "id": "profileDacpac", "fileName": "Commerce.Storefront.ProfileDatabase.dacpac", "databaseId": "CommerceProfilesDB"  }   ]
                ]   
            }   
        ],
        [   {   "id": "foundationDatabaseScripts",
                "path": "C:\\Projects\\Sitecore.Demo.Retail\\src\\Foundation\\Commerce\\Database",
                "files": [
                    [   {   "id": "commerceEngineScript", "fileName": "CommerceServicesDbScript.sql", "databaseId": "commerceEngineGlobalDB", "useDatabaseName": false  }   ]
                ]   
            }   
        ],
        [   {   "id": "commerceServerResources",
                "path": "C:\\Projects\\Sitecore.Demo.Retail\\src\\Project\\Retail\\Database",
                "files": [
                    [   {   "id": "catalog",      "fileName": "Catalog.xml"   }   ],
				    [   {   "id": "inventory",    "fileName": "Inventory.xml" }   ],
				    [	{   "id": "profiles",     "fileName": "Profiles.xml"  }   ]
                ]   
            }   
        ],
        [   {   "id": "dotnet",
                "path": "c:\\Program Files\\dotnet",
                "files": [
                    [   {   "id": "exe",      "fileName": "dotnet.exe"   }   ]
                ]   
            }   
        ],
        [   {   "id": "commerceEngineProject",
                "path": "C:\\projects\\Sitecore.Demo.Retail\\src\\Project\\Retail\\Engine",
                "files": []   
            }   
        ],  
        [   {   "id": "solutionRoot",
                "path": "C:\\Projects\\Sitecore.Demo.Retail\\",
                "files": []   
            }   
        ] 
    ],
    "accounts": [
        [   {   "id": "runTime", "Domain":  ".", "username": "HabitatRunTimeUser", "password": "pass@word1", "fullname": "HabitatRunTimeUser", "description": "Commerce Server Run Time Service Account", "defaultGroupMembership":  "Administrators", "defaultSqlServerRole": "sysadmin"  }   ]
    ],
    "iis": {
        "appPools": [
            [   {   "id": "sitecore", "name": "habitat.dev.local", "managedRuntimeVersion": "v4.0", "accountId": "runTime" }   ],
            [   {   "id": "commerceServerServices", "name": "habitat.csservices.dev.local", "managedRuntimeVersion": "v4.0", "accountId": "runTime" }   ],
            [   {   "id": "commerceEngine", "name": "habitat.commerceengine.dev.local", "managedRuntimeVersion": "", "accountId": "runTime" }   ]

        ],
        "websites": [
            [   {   "id": "sitecore", 
                    "siteName": "habitat.dev.local", 
                    "physicalPath": "C:\\inetpub\\wwwroot\\habitat.dev\\Website" ,
                    "appPoolId":  "sitecore",
                    "bindings": [
                        [   {   "protocol": "http", "ipAddress": "*", "port": "80", "hostName": "habitat.dev.local"  }   ],
                        [   {   "protocol": "http", "ipAddress": "*", "port": "80", "hostName": "retail.dev.local"  }   ]
                    ]
                }
            ],
            [   {   "id": "commerceServerServices", 
                    "siteName": "habitat.csservices.dev.local", 
                    "physicalPath": "C:\\inetpub\\wwwroot\\sc82u1\\CSServices" ,
                    "appPoolId":  "commerceServerServices",
                    "bindings": [
                        [   {   "protocol": "http", "ipAddress": "*", "port": "1004", "hostName": "habitat.csservices.dev.local"  }   ]
                    ]
                }
            ],
            [   {   "id": "commerceEngine", 
                    "siteName": "habitat.commerceengine.dev.local", 
                    "physicalPath": "C:\\inetpub\\wwwroot\\habitat.dev\\CommerceEngine" ,
                    "appPoolId":  "commerceEngine",
                    "bindings": [
                        [   {   "protocol": "http", "ipAddress": "*", "port": "5000", "hostName": "habitat.commerceengine.dev.local"  }   ]
                    ]
                }
            ]
        ],
        "hostEntries": [
            [   {   "ipAddress": "127.0.0.1", "hostName": "habitat.dev.local", "description": "Sitecore site"   }   ],
            [   {   "ipAddress": "127.0.0.1", "hostName": "retail.dev.local", "description": "Sitecore commerce site"   }   ],
            [   {   "ipAddress": "127.0.0.1", "hostName": "habitat.csservices.dev.local", "description": "Sitecore commerce server services site"   }   ],
            [   {   "ipAddress": "127.0.0.1", "hostName": "habitat.commerceengine.dev.local", "description": "Sitecore commerce engine site"   }   ]
        ],
        "certificates": [
            [   {   "DnsName": "retail.dev.local", "siteName": "habitat.dev.local"  }   ]
        ]    
    },
    "databases": [
        [   {   "id": "commerceAdminDB", "server": ".\\SQLEXPRESS", "name": "MSCS_Admin"    }   ],
        [   {   "id": "commerceCatalogDB", "server": ".\\SQLEXPRESS", "name": "demo.local_CommerceServer.ProductCatalog"    }   ],
        [   {   "id": "commerceProfilesDB", "server": ".\\SQLEXPRESS", "name": "demo.local_CommerceServer.Profiles"    }   ],
        [   {   "id": "commerceEngineGlobalDB", "server": ".\\SQLEXPRESS", "name": "demo.local_SitecoreCommerce.Global"    }   ],
        [   {   "id": "commerceEngineSharedEnvironmentDB", "server": ".\\SQLEXPRESS", "name": "demo.local_SitecoreCommerce.SharedEnvironments"    }   ]     
    ],
    "sitecoreCommerce": {
        "csInstallerConfig":  {   "adminDatabaseId": "commerceAdminDB", "windowsSecurity": "yes", "username": "", "password": "", "stagingServiceAccountId": "runTime" },
        "csSite":  {   "name": "Habitat", "catalogDatabaseId": "commerceCatalogDB", "profileDatabaseId": "CommerceProfilesDB", "csServicesWebsiteId": "commerceServerServices", "runTimeAppPoolId": "commerceServerServices", "catalogAppPoolId": "commerceServerServices", "profilesAppPoolId": "commerceServerServices" }
    }
}